cowork/__init__.py
cowork/version.py
open_cowork-0.0.0.dist-info/licenses/LICENSE
open_cowork-0.0.0.dist-info/METADATA
open_cowork-0.0.0.dist-info/WHEEL
open_cowork-0.0.0.dist-info/entry_points.txt
open_cowork-0.0.0.dist-info/top_level.txt
open_cowork-0.0.0.dist-info/RECORD
