Metadata-Version: 2.4
Name: open-cowork
Version: 0.0.0
Summary: Open-Cowork
Author: open-cowork team
Author-email: xx@yy.com
License: Apache License 2.0
Project-URL: Homepage, https://github.com
Keywords: Open-Cowork,Software
Classifier: Development Status :: 4 - Beta
Classifier: Operating System :: OS Independent
Classifier: Programming Language :: Python :: 3
Classifier: Programming Language :: Python :: 3.10
Classifier: Programming Language :: Python :: 3.11
Classifier: Programming Language :: Python :: 3.12
Classifier: Programming Language :: Python :: 3.13
Classifier: License :: OSI Approved :: Apache Software License
Requires-Python: >=3.10
License-File: LICENSE
Provides-Extra: docs
Provides-Extra: tests
Dynamic: license-file
